faster_translate/__init__.py
faster_translate/model.py
faster_translate/utils.py
faster_translate-1.0.2.dist-info/LICENSE
faster_translate-1.0.2.dist-info/METADATA
faster_translate-1.0.2.dist-info/WHEEL
faster_translate-1.0.2.dist-info/top_level.txt
faster_translate-1.0.2.dist-info/RECORD
