Metadata-Version: 2.2
Name: faster-translate
Version: 1.0.2
Summary: A high-performance translation library using CTTranslate2 and vLLM.
Author-email: Sawradip Saha <sawradip0@gmail.com>
License: MIT License
Project-URL: Homepage, https://github.com/sawradip/faster-translate
Project-URL: Bug Tracker, https://github.com/sawradip/faster-translate/issues
Project-URL: Documentation, https://github.com/sawradip/faster-translate/blob/main/README.md
Keywords: translation,huggingface,nlp,ctranslate2,vllm
Classifier: Programming Language :: Python :: 3
Classifier: License :: OSI Approved :: MIT License
Classifier: Operating System :: OS Independent
Classifier: Natural Language :: English
Classifier: Topic :: Scientific/Engineering :: Artificial Intelligence
Classifier: Intended Audience :: Developers
Classifier: Intended Audience :: Science/Research
Requires-Python: >=3.8
License-File: LICENSE
Requires-Dist: transformers>=4.36.1
Requires-Dist: ctranslate2>=4.1.0
Requires-Dist: tokenizers>=0.15.2
Requires-Dist: datasets>=2.10.0
Requires-Dist: huggingface_hub>=0.19.0
Requires-Dist: tqdm>=4.64.0
Provides-Extra: normalizer
Requires-Dist: csebuetnlp-normalizer>=1.0.0; extra == "normalizer"
Provides-Extra: vllm
Requires-Dist: vllm>=0.3.0; extra == "vllm"
Provides-Extra: all
Requires-Dist: csebuetnlp-normalizer>=1.0.0; extra == "all"
Requires-Dist: vllm>=0.3.0; extra == "all"
